viceroy-0.3.2.dist-info/METADATA
viceroy-0.3.2.dist-info/RECORD
viceroy-0.3.2.dist-info/metadata.json
viceroy-0.3.2.dist-info/DESCRIPTION.rst
viceroy-0.3.2.dist-info/top_level.txt
viceroy-0.3.2.dist-info/WHEEL
viceroy/api.py
viceroy/__init__.py
viceroy/exceptions.py
viceroy/constants.py
viceroy/scanner.py
viceroy/tests/__init__.py
viceroy/tests/core.py
viceroy/tests/jasmine.py
viceroy/tests/django.py
viceroy/tests/qunit.py
viceroy/tests/js/jasmine/specrunner.html
viceroy/tests/js/jasmine/src/version.js
viceroy/tests/js/jasmine/src/console/ConsoleReporter.js
viceroy/tests/js/jasmine/src/console/requireConsole.js
viceroy/tests/js/jasmine/src/core/ExceptionFormatter.js
viceroy/tests/js/jasmine/src/core/ObjectContaining.js
viceroy/tests/js/jasmine/src/core/ExpectationResult.js
viceroy/tests/js/jasmine/src/core/Spec.js
viceroy/tests/js/jasmine/src/core/JsApiReporter.js
viceroy/tests/js/jasmine/src/core/Suite.js
viceroy/tests/js/jasmine/src/core/Clock.js
viceroy/tests/js/jasmine/src/core/Any.js
viceroy/tests/js/jasmine/src/core/ReportDispatcher.js
viceroy/tests/js/jasmine/src/core/DelayedFunctionScheduler.js
viceroy/tests/js/jasmine/src/core/SpyStrategy.js
viceroy/tests/js/jasmine/src/core/base.js
viceroy/tests/js/jasmine/src/core/CallTracker.js
viceroy/tests/js/jasmine/src/core/PrettyPrinter.js
viceroy/tests/js/jasmine/src/core/Timer.js
viceroy/tests/js/jasmine/src/core/Env.js
viceroy/tests/js/jasmine/src/core/Expectation.js
viceroy/tests/js/jasmine/src/core/util.js
viceroy/tests/js/jasmine/src/core/QueueRunner.js
viceroy/tests/js/jasmine/src/core/requireCore.js
viceroy/tests/js/jasmine/src/core/MockDate.js
viceroy/tests/js/jasmine/src/core/matchers/matchersUtil.js
viceroy/tests/js/jasmine/src/core/matchers/toEqual.js
viceroy/tests/js/jasmine/src/core/matchers/toBeLessThan.js
viceroy/tests/js/jasmine/src/core/matchers/toThrowError.js
viceroy/tests/js/jasmine/src/core/matchers/toBeUndefined.js
viceroy/tests/js/jasmine/src/core/matchers/toMatch.js
viceroy/tests/js/jasmine/src/core/matchers/toThrow.js
viceroy/tests/js/jasmine/src/core/matchers/toBeDefined.js
viceroy/tests/js/jasmine/src/core/matchers/toBe.js
