Metadata-Version: 2.0
Name: viceroy
Version: 0.3.2
Summary: UNKNOWN
Home-page: https://github.com/ojii/viceory
Author: Jonas Obrist
Author-email: ojiidotch@gmail.com
License: BSD
Platform: UNKNOWN
Classifier: Programming Language :: Python :: 3.3
Classifier: Programming Language :: Python :: 3.4
Requires-Dist: selenium
Requires-Dist: slimit
